[
  {
    "name": "计算机科学与技术",
    "university": "清华大学",
    "degree": "学士",
    "department": "计算机科学与技术系",
    "duration": 4,
    "description": "培养具备计算机科学与技术领域扎实理论基础和工程实践能力的高素质人才"
  },
  {
    "name": "计算机科学与技术",
    "university": "北京大学",
    "degree": "学士",
    "department": "信息科学技术学院",
    "duration": 4,
    "description": "培养具有深厚计算机科学理论功底和创新能力的拔尖人才"
  },
  {
    "name": "计算机科学与技术",
    "university": "浙江大学",
    "degree": "学士",
    "department": "计算机科学与技术学院",
    "duration": 4,
    "description": "培养具备计算机系统设计、开发与应用能力的高素质工程技术人才"
  },
  {
    "name": "人工智能",
    "university": "清华大学",
    "degree": "学士",
    "department": "交叉信息研究院",
    "duration": 4,
    "description": "培养人工智能领域理论基础扎实、具有创新能力的专业人才"
  }
]
